onedep_biocuration/__init__.py
onedep_biocuration/api/ContentRequest.py
onedep_biocuration/api/__init__.py
onedep_biocuration/cli/__init__.py
onedep_biocuration/cli/biocuration_cli.py
onedep_biocuration/utils/ApiBase.py
onedep_biocuration/utils/__init__.py
onedep_biocuration_api-0.1.dist-info/DESCRIPTION.rst
onedep_biocuration_api-0.1.dist-info/METADATA
onedep_biocuration_api-0.1.dist-info/RECORD
onedep_biocuration_api-0.1.dist-info/WHEEL
onedep_biocuration_api-0.1.dist-info/entry_points.txt
onedep_biocuration_api-0.1.dist-info/metadata.json
onedep_biocuration_api-0.1.dist-info/top_level.txt
